dummypackage/__init__.py
dummypackage/bar_module.py
dummypackage/foo_module.py
dummypackage/nested/__init__.py
dummypackage/nested/baz_module.py
dummypackage_dummyname-1.5.2.dist-info/LICENSE
dummypackage_dummyname-1.5.2.dist-info/METADATA
dummypackage_dummyname-1.5.2.dist-info/WHEEL
dummypackage_dummyname-1.5.2.dist-info/top_level.txt
dummypackage_dummyname-1.5.2.dist-info/RECORD
