Metadata-Version: 2.1
Name: dummypackage-dummyname
Version: 1.5.2
Summary: A dummy package
Home-page: https://github.com/andres-fr/python3-template
Author: Dummy Name
Author-email: dd@dummysolutions.com
License: UNKNOWN
Platform: UNKNOWN
Classifier: Programming Language :: Python :: 3 :: Only
Classifier: License :: OSI Approved :: GNU General Public License v3 (GPLv3)
Classifier: Operating System :: OS Independent
